roaring_landmask-0.10.1.dist-info/METADATA
roaring_landmask-0.10.1.dist-info/WHEEL
roaring_landmask/__init__.py
roaring_landmask/roaring_landmask.pyd
roaring_landmask-0.10.1.dist-info/RECORD
